rustpy/__init__.py
rustpy/atomic.py
rustpy/atomic_async.py
rustpy/bootstrap.py
rustpy/cli.py
rustpy/db.py
rustpy/db_async.py
rustpy/generator.py
rustpy/setup.py
rustpy/tx_state.py
rustpy/migrations/__init__.py
rustpy/migrations/inspect.py
rustpy/migrations/makemigrations.py
rustpy/migrations/migrate.py
rustpy/migrations/safe_migrate.py
rustpy/migrations/schema.py
rustpy/models/__init__.py
rustpy/models/base.py
rustpy/models/compiler.py
rustpy/models/fields.py
rustpy/models/manager.py
rustpy/models/manager_async.py
rustpy/models/meta.py
rustpy/models/queryset.py
rustpy/models/queryset_async.py
rustpy/models/registry.py
rustpy/models/backend/__init__.py
rustpy/models/backend/aiosqlite.py
rustpy/models/backend/sqlite.py
rustpy2025-0.2.7.dist-info/METADATA
rustpy2025-0.2.7.dist-info/WHEEL
rustpy2025-0.2.7.dist-info/entry_points.txt
rustpy2025-0.2.7.dist-info/top_level.txt
rustpy2025-0.2.7.dist-info/RECORD
