Metadata-Version: 2.4
Name: rustpy2025
Version: 0.2.7
Summary: Django uslubidagi CLI framework va Telegram botlar uchun yordamchi kutubxona, fk yes 
Author: Rustamjon
License: MIT
Project-URL: Homepage, https://www.myrustpyhomes.tech/
Project-URL: Documentation, https://www.myrustpyhomes.tech/doc
Keywords: cli,framework,telegram,aiogram,migrations
Classifier: Programming Language :: Python :: 3
Classifier: Programming Language :: Python :: 3.8
Classifier: Programming Language :: Python :: 3.9
Classifier: Programming Language :: Python :: 3.10
Classifier: License :: OSI Approved :: MIT License
Classifier: Operating System :: OS Independent
Requires-Python: >=3.8
Requires-Dist: aiogram>=3.4.0
Requires-Dist: aiosqlite>=0.17.0
